napalm_eltex2448/__init__.py
napalm_eltex2448/eltex2448.py
napalm_eltex2448/parse.py
napalm_eltex2448/usage.py
napalm_eltex2448/utils/textfsm_templates/show_lldp_neighbors.tpl
napalm_eltex2448/utils/textfsm_templates/show_lldp_neighbors_detail.tpl
napalm_eltex2448-0.1.12.dist-info/licenses/AUTHORS
napalm_eltex2448-0.1.12.dist-info/licenses/LICENSE
napalm_eltex2448-0.1.12.dist-info/METADATA
napalm_eltex2448-0.1.12.dist-info/WHEEL
napalm_eltex2448-0.1.12.dist-info/top_level.txt
napalm_eltex2448-0.1.12.dist-info/RECORD
