Metadata-Version: 2.4
Name: napalm-eltex2448
Version: 0.1.12
Summary: NAPALM driver for Eltex switches
Home-page: https://github.com/noc-uac-ssc/napalm-eltex
Author: UAC-SSC
Author-email: noc@uac-ssc.ru
License: NIT License
Project-URL: Bug Tracker, https://github.com/noc-uac-ssc/napalm-eltex/issues
Classifier: Topic :: Utilities
Classifier: License :: OSI Approved :: MIT License
Classifier: Programming Language :: Python
Classifier: Programming Language :: Python :: 3
Classifier: Programming Language :: Python :: 3.6
Classifier: Programming Language :: Python :: 3.7
Classifier: Programming Language :: Python :: 3.8
Classifier: Programming Language :: Python :: 3.9
Classifier: Programming Language :: Python :: 3.10
Classifier: Operating System :: OS Independent
License-File: LICENSE
License-File: AUTHORS
Requires-Dist: napalm>=3.3
Requires-Dist: pandas>=1.3
Dynamic: author
Dynamic: author-email
Dynamic: classifier
Dynamic: description
Dynamic: description-content-type
Dynamic: home-page
Dynamic: license
Dynamic: license-file
Dynamic: project-url
Dynamic: requires-dist
Dynamic: summary
